{"general":{"playerMoney":10000,"mapSize":2000},"resources":[{"name":"millet","color":"#fdbf6f","symbol":"a","productionTime":15,"isVital":true,"basePrice":20},{"name":"silk","color":"#a6cee3","symbol":"b","productionTime":15,"basePrice":40},{"name":"rice","color":"#cab2d6","symbol":"c","productionTime":12,"isVital":true,"basePrice":10},{"name":"jade","color":"#b2df8a","symbol":"d","productionTime":15,"basePrice":60},{"name":"silk cloth","color":"#1f78b4","symbol":"e","productionTime":10,"productionCost":20,"workshop":"tailor","neededResources":[{"name":"silk","quantity":1}]},{"name":"jade idol","color":"#33a02c","symbol":"f","productionTime":20,"productionCost":20,"workshop":"sculptor","neededResources":[{"name":"jade","quantity":2}]},{"name":"iron","color":"#fb9a99","symbol":"g","productionTime":15,"basePrice":50},{"name":"gold","color":"#ffff00","symbol":"h","productionTime":30,"basePrice":100},{"name":"gold ingot","color":"#ff8000","symbol":"i","productionTime":10,"productionCost":10,"workshop":"foundry","neededResources":[{"name":"gold","quantity":3}]},{"name":"gold statue","color":"#6a3d9a","symbol":"j","productionTime":30,"productionCost":25,"workshop":"sculptor","neededResources":[{"name":"gold ingot","quantity":2},{"name":"jade","quantity":1}]},{"name":"coal","color":"#313131","symbol":"k","productionTime":10,"basePrice":10},{"name":"steel","color":"#ff0000","symbol":"l","productionTime":15,"productionCost":20,"workshop":"foundry","neededResources":[{"name":"coal","quantity":2},{"name":"iron","quantity":1}]},{"name":"wood","color":"#804000","symbol":"m","productionTime":10,"basePrice":15},{"name":"tool","color":"#000080","symbol":"n","productionTime":15,"isVital":true,"productionCost":20,"workshop":"craftman","neededResources":[{"name":"steel","quantity":1},{"name":"wood","quantity":1}]}],"workshops":[{"name":"tailor","price":150},{"name":"sculptor","price":200},{"name":"foundry","price":300},{"name":"craftman","price":350}],"buildings":[{"name":"temple","symbol":"cross","price":800,"needs":[{"name":"rice","weight":2},{"name":"silk cloth","weight":3},{"weight":3,"name":"jade idol"}]},{"name":"palace","symbol":"square","price":2000,"needs":[{"name":"millet","weight":2},{"weight":6,"name":"gold statue"}]},{"name":"civic building","symbol":"triangle-up","price":500,"needs":[{"weight":4,"name":"steel"}]},{"name":"bank","symbol":"diamond","price":1000,"needs":[{"name":"gold ingot","weight":8}]}],"advances":{"0":[{"resourceName":"rice","populationNeedWeight":5,"exploitationNumber":6},{"resourceName":"millet","populationNeedWeight":3,"exploitationNumber":4},{"resourceName":"silk","exploitationNumber":4},{"resourceName":"silk cloth","populationNeedWeight":2,"workshopNumber":1}],"300":[{"resourceName":"jade","exploitationNumber":4},{"resourceName":"jade idol","populationNeedWeight":2,"workshopNumber":2},{"buildingName":"temple","buildingNumber":1}],"600":[{"resourceName":"iron","exploitationNumber":2},{"resourceName":"coal","exploitationNumber":3},{"resourceName":"steel","workshopNumber":1},{"buildingName":"civic building","buildingNumber":2}],"900":[{"resourceName":"wood","exploitationNumber":4},{"resourceName":"tool","populationNeedWeight":2,"workshopNumber":1}],"1201":[{"resourceName":"gold","exploitationNumber":2},{"resourceName":"gold ingot"},{"buildingName":"bank","buildingNumber":2}],"1503":[{"resourceName":"gold statue","populationNeedWeight":1},{"buildingName":"palace","buildingNumber":1}]}}